pressure_test_lib
