Metadata-Version: 2.1
Name: pressure-test-lib
Version: 0.0.3
Summary: 压测包
Home-page: https://github.com/guanmengshi/test
Author: guanmengshi
License: UNKNOWN
Keywords: test,pressure-test
Platform: UNKNOWN
Classifier: Programming Language :: Python :: 3
Classifier: Programming Language :: Python :: 3.7
